lab-7-1/virtual_prototype/modules/performanceCounter/counter.v
module counter #( parameter WIDTH = 8)
                ( input wire reset,
                             clock,
                             enable,
                             direction, /* a 1 is counting up, a 0 is counting down */
                  output reg [WIDTH-1:0] counterValue);

  always @(posedge clock)
    counterValue <= (reset == 1'b1) ? {WIDTH{1'b0}} : 
                    (enable == 1'b0) ? counterValue :
                    (direction == 1'b1) ? counterValue + 1 : counterValue - 1;

endmodule

lab-2/virtual_prototype/modules/performanceCounter/profileCi.v
module profileCi #(parameter[7:0] customId = 8'h00)
    (
        input wire start, clock, reset, stall, busIdle, 
        input wire[31:0] valueA, valueB,
        input wire [7:0] cIn,
        output wire done,
        output wire[31:0] result
    );

    wire [31:0] counterValue0;
    wire [31:0] counterValue1;
    wire [31:0] counterValue2;
    wire [31:0] counterValue3;
    reg  [31:0] stableB;


    counter #(.WIDTH(32)) counter0 (
        .clock(clock),
        .reset(reset || stableB[8]),
        .enable(start && stableB[0]),
        .direction(1'b1),
        .counterValue(counterValue0)
    );

    counter #(.WIDTH(32)) counter1 (
        .clock(clock),
        .reset(reset || stableB[9]),
        .enable(stall && stableB[1]),
        .direction(1'b1),
        .counterValue(counterValue1)
    );

    counter #(.WIDTH(32)) counter2 (
        .clock(clock),
        .reset(reset || stableB[10]),
        .enable(busIdle && stableB[2]),
        .direction(1'b1),
        .counterValue(counterValue2)
    );

    counter #(.WIDTH(32)) counter3 (
        .clock(clock),
        .reset(reset || stableB[11]),
        .enable(start && stableB[3]),
        .direction(1'b1),
        .counterValue(counterValue3)
    );

    assign result = (cIn != customId || start == 1'b0) ? 32'b0: (valueA[1:0] == 2'd0) ? counterValue0 : (valueA[1:0] == 2'd1) ? counterValue1 : (valueA[1:0] == 2'd2) ? counterValue2 : counterValue3;

    assign done = (cIn != customId || start == 1'b0) ? 1'b0 : 1'b1;

    always @(posedge clock) begin

        if(cIn == customId && start == 1'b1) begin
            stableB <= valueB;
        end

    end

endmodule

lab-2/virtual_prototype/modules/performanceCounter/profileCi_tb.v
`timescale 1ps/1ps

module profileCi_tb;

    // Define the input signals as reg
    reg clock, reset, stall, busIdle, start;
    reg[31:0] valueA, valueB;
    reg[7:0] cIn;

    // Define the output signals as wires
    wire        done;
    wire[31:0]  result;

    profileCi #(.customId(8'd62)) dut
        (.reset(reset),
        .clock(clock),
        .stall(stall),
        .busIdle(busIdle),
        .start(start),
        .cIn(cIn),
        .valueA(valueA),
        .valueB(valueB),
        .done(done),
        .result(result)
        );

    // Set the rst to 1. keep the rst to 1 for 4 cycles. Set the reset to 0. Start "forever" with the clock
    initial
    begin
        reset = 1'b1;
        clock = 1'b0;
        repeat (4) #5 clock = ~clock;
        reset = 1'b0;
        forever #5 clock = ~clock;
    end


    // Instantiate the device under test

    initial
    begin

        busIdle = 1'b0;
        stall = 1'b0;

        
        // Set cIn to the custom instruction
        cIn = 8'd62;

        // Set regB s.t. all the counters are enabled
        valueB = 32'd15;

        // Set regA to read cnt 0
        valueA = 32'd0;

        // Set the start signal to 1
        start = 1'b1;

        @(negedge reset);
        repeat(4) @(negedge clock);

        busIdle = 1'b1;

        repeat(3) @(negedge clock);

        stall = 1'b1;

        // Read cnt 1
        valueA = 32'd1;

        repeat(5) @(negedge clock);

        // Read cnt 2
        valueA = 32'd0;

        repeat(2) @(negedge clock);

        // Set Cin to another instruction
        cIn = 8'd8;

        repeat(10) @(negedge clock);

        $finish;
    end

    initial
    begin
    $dumpfile("profileCi.vcd");
    $dumpvars(1,dut);
    end

endmodule

lab-2/virtual_prototype/modules/performanceCounter/profileCi.vcd
$date
	Tue Mar 12 19:25:25 2024
$end
$version
	Icarus Verilog
$end
$timescale
	1ps
$end
$scope module profileCi_tb $end
$scope module dut $end
$var wire 1 ! busIdle $end
$var wire 8 " cIn [7:0] $end
$var wire 1 # clock $end
$var wire 1 $ reset $end
$var wire 1 % stall $end
$var wire 1 & start $end
$var wire 32 ' valueA [31:0] $end
$var wire 32 ( valueB [31:0] $end
$var wire 32 ) result [31:0] $end
$var wire 1 * done $end
$var wire 32 + counterValue3 [31:0] $end
$var wire 32 , counterValue2 [31:0] $end
$var wire 32 - counterValue1 [31:0] $end
$var wire 32 . counterValue0 [31:0] $end
$var parameter 8 / customId $end
$var reg 32 0 stableB [31:0] $end
$upscope $end
$upscope $end
$enddefinitions $end
$comment Show the parameter values. $end
$dumpall
b111110 /
$end
#0
$dumpvars
bx 0
bx .
bx -
bx ,
bx +
1*
bx )
b1111 (
b0 '
1&
0%
1$
0#
b111110 "
0!
$end
#5
b0 )
b0 .
b0 -
b0 ,
b0 +
b1111 0
1#
#10
0#
#15
1#
#20
0$
0#
#25
b1 )
b1 .
b1 +
1#
#30
0#
#35
b10 )
b10 +
b10 .
1#
#40
0#
#45
b11 )
b11 .
b11 +
1#
#50
0#
#55
b100 )
b100 +
b100 .
1#
#60
1!
0#
#65
b101 )
b101 .
b1 ,
b101 +
1#
#70
0#
#75
b110 )
b110 +
b10 ,
b110 .
1#
#80
0#
#85
b111 )
b111 .
b11 ,
b111 +
1#
#90
b0 )
b1 '
1%
0#
#95
b1 )
b1000 +
b100 ,
b1 -
b1000 .
1#
#100
0#
#105
b10 )
b1001 .
b10 -
b101 ,
b1001 +
1#
#110
0#
#115
b11 )
b1010 +
b110 ,
b11 -
b1010 .
1#
#120
0#
#125
b100 )
b1011 .
b100 -
b111 ,
b1011 +
1#
#130
0#
#135
b101 )
b1100 +
b1000 ,
b101 -
b1100 .
1#
#140
b1100 )
b0 '
0#
#145
b1101 )
b1101 .
b110 -
b1001 ,
b1101 +
1#
#150
0#
#155
b1110 )
b1110 +
b1010 ,
b111 -
b1110 .
1#
#160
b0 )
0*
b1000 "
0#
#165
b1111 .
b1000 -
b1011 ,
b1111 +
1#
#170
0#
#175
b10000 +
b1100 ,
b1001 -
b10000 .
1#
#180
0#
#185
b10001 .
b1010 -
b1101 ,
b10001 +
1#
#190
0#
#195
b10010 +
b1110 ,
b1011 -
b10010 .
1#
#200
0#
#205
b10011 .
b1100 -
b1111 ,
b10011 +
1#
#210
0#
#215
b10100 +
b10000 ,
b1101 -
b10100 .
1#
#220
0#
#225
b10101 .
b1110 -
b10001 ,
b10101 +
1#
#230
0#
#235
b10110 +
b10010 ,
b1111 -
b10110 .
1#
#240
0#
#245
b10111 .
b10000 -
b10011 ,
b10111 +
1#
#250
0#
#255
b11000 +
b10100 ,
b10001 -
b11000 .
1#
