lab-6/virtual_prototype/modules/DMA/dma_new.v
module dma_new (input wire  clock, reset,
                            readBusStartAddress, writeBusStartAddress,
                            readMemoryStartAddress, writeMemoryStartAddress,
                            readBlockSize, writeBlockSize,
                            readBurstSize, writeBurstSize,
                            readStatusRegister, writeControlRegister,
                input wire dmaAckBusIn, dmaBusErrorIn, dmaBusyIn,
                input wire [31:0] ci_valueBIn, ssram_outBIn,
                output wire writeEnableBOut,
                output wire dmaRequestBusOut, dmaBeginTransactionOut, dmaReadNotWriteOut,
                output wire [3:0] dmaByteEnablesOut,
                output wire [7:0] dmaBurstSizeOut,
                output wire [8:0] ssram_addressBOut,
                output wire [31:0] ci_resultOut,
                input wire dmaDataValidIn,dmaEndTransactionIn,
                output wire dmaDataValidOut,dmaEndTransactionOut,
                input wire [31:0] dmaAddressDataIn,
                output wire [31:0] dmaAddressDataOut);

    // declare FSM states
    parameter IDLE                      = 9'b0000_00000;
    parameter WAIT_GRANT_READ           = 9'b0001_00001;
    parameter WAIT_GRANT_WRITE          = 9'b0010_00001;
    parameter BEGIN_TRANSACTION_READ    = 9'b0011_01010;
    parameter BEGIN_TRANSACTION_WRITE   = 9'b0100_01000;
    parameter READ_BURST                = 9'b0101_00000;
    parameter WRITE_BURST               = 9'b0110_00100;
    parameter NEW_REQUEST_WRITE         = 9'b0111_10000;
    parameter END_TRANSACTION_WRITE     = 9'b1000_10000;
    parameter ERROR                     = 9'b1001_10000;

    reg [8:0] state;
    assign dmaRequestBusOut = state[0];
    assign dmaReadNotWriteOut = state[1];
    assign dmaDataValidOut = state[2];
    assign dmaBeginTransactionOut = state[3];
    assign dmaEndTransactionOut = state[4];
    assign writeEnableBOut = (state == READ_BURST) ? dmaDataValidIn : 1'b0;

    // declare internal registers
    reg [31:0] busStartAddress;
    reg [8:0] memoryStartAddress;
    reg [9:0] blockSize;
    reg [7:0] burstSize;
    reg [31:0] status;
    reg [1:0] control;
    reg [31:0] result_reg;

    // dma config read/write
    always @(posedge clock or posedge reset)
    begin
        if (reset) begin
            result_reg <= 32'h0000_0000;
            busStartAddress <= 32'h0000_0000;
            memoryStartAddress <= 9'h000;
            blockSize <= 10'h000;
            burstSize <= 8'h00;
            control <= 2'b00;
        end

        // handle register reading (only signal can be high at the same time due to custom instruction)
        else if (readBusStartAddress)
            result_reg <= busStartAddress;
        else if (readMemoryStartAddress)
            result_reg <= {23'h000000,memoryStartAddress};
        else if (readBlockSize)
            result_reg <= {22'h000000,blockSize};
        else if (readBurstSize)
            result_reg <= {24'h000000,burstSize};
        else if (readStatusRegister)
            result_reg <= status;

        // handle register writing
        else if (writeBusStartAddress)
            busStartAddress <= ci_valueBIn;
        else if (writeMemoryStartAddress)
            memoryStartAddress <= ci_valueBIn[8:0];
        else if (writeBlockSize)
            blockSize <= ci_valueBIn[9:0];
        else if (writeBurstSize)
            burstSize <= ci_valueBIn[7:0];
        else if (writeControlRegister)
            control <= ci_valueBIn[1:0];
        else
            //result_reg <= result;
            control <= 2'b00; // take the start instruction away
    end
    assign ci_resultOut = result_reg;


    // FSM registers
    reg [7:0] burstSize_counter;
    reg [7:0] current_transaction_burstSize;
    reg [9:0] resting_blockSize;
    reg [8:0] memoryAddress;
    reg [31:0] busAddress;

    reg [3:0] dmaByteEnables_reg;
    reg [7:0] dmaBurstSize_reg;
    reg [31:0] dmaAddressData_reg;

    // assign FSM registers to outputs
    assign dmaByteEnablesOut = dmaByteEnables_reg;
    assign dmaBurstSizeOut = dmaBurstSize_reg;
    assign dmaAddressDataOut = dmaAddressData_reg;
    assign ssram_addressBOut = memoryAddress;

    // DMA FSM
    always @(posedge clock or posedge reset) begin
        if (reset) begin
            resting_blockSize <= 10'h000;
            burstSize_counter <= 8'h00;
            current_transaction_burstSize <= 8'h00;
            memoryAddress <= 9'h000;
            status <= 32'h0000_0000;

            dmaByteEnables_reg <= 4'b0000;
            dmaBurstSize_reg <= 8'h00;
            dmaAddressData_reg <= 32'h0000_0000;

            state <= IDLE;
        end

        else begin
            case (state)
                IDLE: begin
                    if ((control[0] && ~control[1]) || (~control[0] && control[1])) begin
                        status <= 32'h0000_0001;
                        memoryAddress <= memoryStartAddress;
                        busAddress <= busStartAddress;
                        resting_blockSize <= blockSize;
                        if (control[0]) state <= WAIT_GRANT_READ;
                        else state <= WAIT_GRANT_WRITE;
                    end else begin
                        memoryAddress <= 9'h000;
                        busAddress <= 32'h0000_0000;

                        dmaByteEnables_reg <= 4'b0000;
                        dmaBurstSize_reg <= 8'h00;
                        dmaAddressData_reg <= 32'h0000_0000;
                    end
                end

                WAIT_GRANT_READ: begin
                    if (dmaAckBusIn) begin
                        dmaByteEnables_reg <= 4'b1111;
                        if ((burstSize + 1) <= (resting_blockSize)) begin
                            dmaBurstSize_reg <= burstSize;
                            current_transaction_burstSize <= burstSize;
                            resting_blockSize <= resting_blockSize - (burstSize + 1);
                        end else begin
                            dmaBurstSize_reg <= (resting_blockSize - 1);
                            current_transaction_burstSize <= (resting_blockSize - 1);
                            resting_blockSize <= 10'h000;
                        end
                        burstSize_counter <= 8'h00;
                        dmaAddressData_reg <= busAddress;
                        state <= BEGIN_TRANSACTION_READ;
                    end
                end

                WAIT_GRANT_WRITE: begin
                    if (dmaAckBusIn) begin
                        dmaByteEnables_reg <= 4'b1111;
                        if ((burstSize + 1) <= (resting_blockSize)) begin
                            dmaBurstSize_reg <= burstSize;
                            current_transaction_burstSize <= burstSize;
                            resting_blockSize <= resting_blockSize - (burstSize + 1);
                        end else begin
                            dmaBurstSize_reg <= (resting_blockSize - 1);
                            current_transaction_burstSize <= (resting_blockSize - 1);
                            resting_blockSize <= 10'h000;
                        end
                        burstSize_counter <= 8'h00;
                        dmaAddressData_reg <= busAddress;
                        state <= BEGIN_TRANSACTION_WRITE;
                    end
                end

                BEGIN_TRANSACTION_READ: begin
                    dmaByteEnables_reg <= 4'b0000;
                    dmaBurstSize_reg <= 8'h00;
                    burstSize_counter <= 8'h00;
                    dmaAddressData_reg <= 32'h0000_0000;
                    state <= READ_BURST;
                end

                BEGIN_TRANSACTION_WRITE: begin
                    dmaByteEnables_reg <= 4'b0000;
                    dmaBurstSize_reg <= 8'h00;
                    burstSize_counter <= 8'h00;
                    dmaAddressData_reg <= ssram_outBIn;
                    memoryAddress <= memoryAddress + 1;
                    state <= WRITE_BURST;
                end

                READ_BURST: begin
                    if (dmaBusErrorIn) state <= ERROR;
                    else begin
                        if (dmaDataValidIn) begin
                            memoryAddress <= memoryAddress + 1;
                        end
                        if (dmaEndTransactionIn) begin
                            if (resting_blockSize == 10'h000) begin
                                status <= 32'h0000_0000;
                                state <= IDLE;
                            end
                            else begin // request a new read transfer with updated busAddress
                                //busAddress <= busAddress + (burstSize + 1)
                                busAddress <= busAddress + (burstSize << 2) + 4; // bus addressing in bytes
                                state <= WAIT_GRANT_READ;
                            end
                        end
                    end
                end

                WRITE_BURST: begin
                    if (dmaBusErrorIn) state <= ERROR;
                    else begin
                        if (~dmaBusyIn) begin
                            if (burstSize_counter == current_transaction_burstSize) begin
                                dmaAddressData_reg <= 32'h0000_0000;
                                if (resting_blockSize == 10'h00) state <= END_TRANSACTION_WRITE;
                                else state <= NEW_REQUEST_WRITE;
                            end else begin
                                memoryAddress <= memoryAddress + 1;
                                dmaAddressData_reg <= ssram_outBIn;
                                burstSize_counter <= burstSize_counter + 1;
                            end
                        end
                    end
                end

                NEW_REQUEST_WRITE: begin
                    if (dmaBusErrorIn) state <= ERROR;
                    else begin
                        //memoryAddress <= memoryAddress + 1;
                        busAddress <= busAddress + (burstSize << 2) + 4; // bus addressing in bytes
                        state <= WAIT_GRANT_WRITE;
                    end
                end

                END_TRANSACTION_WRITE: begin
                    status <= 32'h0000_0000;
                    state <= IDLE;
                end

                ERROR: begin
                    status <= 32'h0000_0002;
                    state <= IDLE;
                end

                default: state <= IDLE;

            endcase
        end

    end



endmodule

lab-6/virtual_prototype/modules/DMA/dualPortSSRAM.v
module dualPortSSRAM #( parameter bitwidth = 8, parameter nrOfEntries = 512, parameter readAfterWrite = 0 )
( 
    input wire clockA, clockB, writeEnableA, writeEnableB,
    input wire [$clog2(nrOfEntries)-1 : 0] addressA, addressB,
    input wire [bitwidth-1 : 0] dataInA, dataInB,
    output reg [bitwidth-1 : 0] dataOutA, dataOutB
);

    reg [bitwidth-1 : 0] memoryContent [nrOfEntries-1 : 0];

  
    always @(posedge clockA) begin
        if (writeEnableA == 1'b1) memoryContent[addressA] = dataInA;
        dataOutA = memoryContent[addressA];
    end

    always @(posedge clockB) begin
        if (writeEnableB == 1'b1) memoryContent[addressB] = dataInB;
        dataOutB = memoryContent[addressB];
    end

    /* always @(posedge clockA)
    begin   
        if (writeEnableA) 
        begin
            memoryContent[addressA] <= dataInA;
            dataOutA <= dataInA;
        end
        else
        begin
            dataOutA <= memoryContent[addressA];
        end
    end


    always @(negedge clockB)
    begin   
        if (writeEnableB) 
        begin
            memoryContent[addressB] <= dataInB;
            dataOutB <= dataInB;
        end
        else
        begin
            dataOutB <= memoryContent[addressB];
        end
    end */


endmodule

lab-6/virtual_prototype/modules/DMA/ramDmaCi_new.v
module ramDmaCi_new #( parameter [7:0] customId = 8'h00)
                 ( input wire start, clock, reset,
                   input wire [31:0] valueA, valueB,
                   input wire [7:0] ciN,
                   output wire done,
                   output wire [31:0] result,


                   input wire dmaAckBusIn,
                   input wire dmaBusErrorIn,
                   input wire dmaBusyIn,
                   input wire dmaEndTransactionIn,
                   input wire dmaDataValidIn,
                   input wire [31:0] dmaAddressDataIn,

                   output wire dmaRequestBusOut,
                   output wire dmaBeginTransactionOut,
                   output wire dmaEndTransactionOut,
                   output wire dmaReadNotWriteOut,
                   output wire dmaDataValidOut,
                   output wire [7:0] dmaBurstSizeOut,
                   output wire [3:0] dmaByteEnablesOut,
                   output wire [31:0] dmaAddressDataOut);


    // Define the CI signals
    wire s_isMyCi = (ciN == customId) ? start : 1'b0;
    wire writeAction = valueA[9] && s_isMyCi;
    wire writeEnableA = (valueA[12:10] == 3'b000) && writeAction;

    reg done_reg; // delayed by 1 cycle with respect to s_isMyCi
    assign done = (writeAction == 1'b1) ? s_isMyCi : done_reg; // read action takes 2 cycles

    always @(posedge clock or posedge reset)
    begin
        if (reset)
            done_reg <= 1'b0;
        else
            done_reg <= s_isMyCi;
    end

    wire [31:0] ssram_outA;
    wire [31:0] dmaControllerOut;
    assign result = (done == 1'b0) ? 32'h0000_0000 : ((valueA[12:10] == 3'b0) ? ssram_outA : dmaControllerOut);


    // Define the signals to interact with the DMA controller
    wire sigBusStartAddress = (valueA[12:10] == 3'b001) && s_isMyCi;
    wire readBusStartAddress = sigBusStartAddress && ~valueA[9];
    wire writeBusStartAddress = sigBusStartAddress && valueA[9];

    wire sigMemoryStartAddress = (valueA[12:10] == 3'b010) && s_isMyCi;
    wire readMemoryStartAddress = sigMemoryStartAddress && ~valueA[9];
    wire writeMemoryStartAddress = sigMemoryStartAddress && valueA[9];

    wire sigBlockSize = (valueA[12:10] == 3'b011) && s_isMyCi;
    wire readBlockSize= sigBlockSize && ~valueA[9];
    wire writeBlockSize= sigBlockSize && valueA[9];

    wire sigBurstSize= (valueA[12:10] == 3'b100) && s_isMyCi;
    wire readBurstSize= sigBurstSize && ~valueA[9];
    wire writeBurstSize= sigBurstSize && valueA[9];

    wire sigOther= (valueA[12:10] == 3'b101) && s_isMyCi;
    wire readStatusRegister= sigOther && ~valueA[9];
    wire writeControlRegister = sigOther && valueA[9];

    // Define the signals between SSRAM and DMA controller
    wire writeEnableB;
    wire [8:0] addressB;
    wire [31:0] ssram_outB;

    // Register the bus inputs
    reg [31:0] dmaAddressDataIn_reg;
    reg dmaEndTransactionIn_reg;
    reg dmaDataValidIn_reg;

    always @(posedge clock or posedge reset)
    begin
        if (reset) begin
            dmaAddressDataIn_reg <= 32'h0;
            dmaEndTransactionIn_reg <= 1'h0;
            dmaDataValidIn_reg <= 1'h0;
        end else begin
            dmaAddressDataIn_reg <= dmaAddressDataIn;
            dmaEndTransactionIn_reg <= dmaEndTransactionIn;
            dmaDataValidIn_reg <= dmaDataValidIn;
        end
    end

    // Instantiate the SSRAM
    dualPortSSRAM #(.bitwidth(32), .nrOfEntries(512)) ssram (
        .clockA(clock),
        .clockB(clock),
        .writeEnableA(writeEnableA),
        .writeEnableB(writeEnableB),
        .addressA(valueA[8:0]),
        .addressB(addressB),
        .dataInA(valueB),
        .dataInB(dmaAddressDataIn_reg),
        .dataOutA(ssram_outA),
        .dataOutB(ssram_outB)
    );

    // Instantiate the DMA controller with flip-flop registered bus inputs
    dma_new DMA (
        .clock(clock),
        .reset(reset),
        .readBusStartAddress(readBusStartAddress),
        .writeBusStartAddress(writeBusStartAddress),
        .readMemoryStartAddress(readMemoryStartAddress),
        .writeMemoryStartAddress(writeMemoryStartAddress),
        .readBlockSize(readBlockSize),
        .writeBlockSize(writeBlockSize),
        .readBurstSize(readBurstSize),
        .writeBurstSize(writeBurstSize),
        .readStatusRegister(readStatusRegister),
        .writeControlRegister(writeControlRegister),
        .dmaAckBusIn(dmaAckBusIn),
        .dmaAddressDataIn(dmaAddressDataIn_reg),
        .dmaBusErrorIn(dmaBusErrorIn),
        .dmaBusyIn(dmaBusyIn),
        .dmaDataValidIn(dmaDataValidIn_reg),
        .dmaEndTransactionIn(dmaEndTransactionIn_reg),
        .ci_valueBIn(valueB),
        .ssram_outBIn(ssram_outB),
        .writeEnableBOut(writeEnableB),
        .ci_resultOut(dmaControllerOut),
        .ssram_addressBOut(addressB),
        .dmaRequestBusOut(dmaRequestBusOut),
        .dmaBeginTransactionOut(dmaBeginTransactionOut),
        .dmaReadNotWriteOut(dmaReadNotWriteOut),
        .dmaByteEnablesOut(dmaByteEnablesOut),
        .dmaBurstSizeOut(dmaBurstSizeOut),
        .dmaDataValidOut(dmaDataValidOut),
        .dmaEndTransactionOut(dmaEndTransactionOut),
        .dmaAddressDataOut(dmaAddressDataOut)
    );
endmodule

lab-6/virtual_prototype/modules/DMA/ramDma_write_tb_copy.v
`timescale 1ns / 1ps

module dma_controller_tb;

// Parameters
parameter customIdCPU = 8'hfd;
parameter customIdDMA = 8'hfe;

// Inputs
reg start;
reg clock;
reg reset;
reg [31:0] valueA;
reg [31:0] valueB;
reg [7:0] ciN;
reg transactionGranted;
reg endTransactionIn;
reg dataValidIn;
reg busErrorIn;
reg busyBitIn;
reg beginTransactionIn;
reg [31:0] addressDataIn;
integer i,j,burstsizeout;


// Outputs
wire done;
wire [31:0] result;
wire requestTransaction;
wire beginTransactionOut;
wire [7:0] burstSizeOut;
wire dataValidOut;
wire [31:0] addressDataOut;
wire endTransaction;
wire[3:0] byteEnable;


wire dataValid;
wire [31:0] addressData;

assign dataValid = dataValidIn| dataValidOut;
assign addressData = addressDataIn | addressDataOut;



initial begin
    $dumpfile("ramDmaCiCopy.vcd");
    $dumpvars(0, dma_controller_tb);
end

// Instantiate the Unit Under Test (UUT)
ramDmaCi_new #(
    //.customIdCPU(customIdCPU),
    .customId(customIdDMA)
) uut (
    .start(start),
    .clock(clock),
    .reset(reset),
    .valueA(valueA),
    .valueB(valueB),
    .ciN(ciN),
    .dmaAckBusIn(transactionGranted),
    .dmaEndTransactionIn(endTransactionIn),
    .dmaDataValidIn(dataValid),
    .dmaBusErrorIn(busErrorIn),
    .dmaBusyIn(busyBitIn),
    .dmaAddressDataIn(addressData),
    .dmaDataValidOut(dataValidOut),
    .done(done),
    .result(result),
    .dmaRequestBusOut(requestTransaction),
    .dmaBeginTransactionOut(beginTransactionOut),
    .dmaBurstSizeOut(burstSizeOut),
    .dmaAddressDataOut(addressDataOut),
    .dmaEndTransactionOut(endTransaction),
    .dmaByteEnablesOut(byteEnable)
);

// Clock generation
always #5 clock = ~clock;

initial begin
    // Initialize Inputs
    start = 0;
    clock = 0;
    reset = 1;
    valueA = 0;
    valueB = 0;
    ciN = 0;
    transactionGranted = 0;
    endTransactionIn = 0;
    dataValidIn = 0;
    busErrorIn = 0;
    busyBitIn = 0;
    beginTransactionIn = 0;
    addressDataIn = 0;
    transactionGranted = 1'b1;
    // Wait 100 ns for global reset to finish
    #100;
    @(negedge clock);
    //initialize memory
    reset = 0;
    start=1;
    ciN=8'hfe;
    for(i = 0; i < 128; i = i + 1) begin
        if(i == 0) begin 
            valueA = 32'd512;
            valueB = 32'b0;
        end else begin
            valueA = i*32'd1 | 32'd512;
            valueB = i*32'd1;
        end
        #10; 
    end
    start=1;
    ciN=0;
    #10;
    // test configuration writes and reads
    start=1;
    ciN=8'hfe;
    valueA=32'h00000600; // write 89 on busstart address
    valueB=32'd89;
    #10;
    start=0;
    ciN=0;
    valueA=0;
    valueB=0;
    #50
    start=1;
    ciN=8'hfe;
    valueA=32'h00000400; //read busstart address
    #10;
    start=0;
    ciN=0;
    valueA=0;
    #50;
    start=1;
    ciN=8'hfe;
    valueA=32'h00000a00; // write 46 on memory start address 
    valueB=32'd0;
    #10;
    start=0;
    ciN=0;
    valueA=0;
    valueB=0;
    #50
    start=1;
    ciN=8'hfe;
    valueA=32'h00000800; //read memory start address
    #10;
    start=0;
    ciN=0;
    valueA=0;
    #50;
    start=1;
    ciN=8'hfe;
    valueA=32'h00000e00; // write 64 on block siye
    valueB=32'd64;
    #10;
    start=0;
    ciN=0;
    valueA=0;
    valueB=0;
    #50
    start=1;
    ciN=8'hfe;
    valueA=32'h00000c00; //read block size
    #10;
    start=0;
    ciN=0;
    valueA=0;
    #50;
    start=1;
    ciN=8'hfe;
    valueA=32'h00001200; // write 7 on burst size
    valueB=32'd7;
    #10;
    start=0;
    ciN=0;
    valueA=0;
    valueB=0;
    #50
    start=1;
    ciN=8'hfe;
    valueA=32'h00001000; //read burst size
    #10;
    start=0;
    ciN=0;
    valueA=0;
    #50
    start=1;
    ciN=8'hfe;
    valueA=32'h00001400; //read status register
    #10;
    start=0;
    ciN=0;
    valueA=0;
    #50;
    start=1;
    ciN=8'hfe;
    valueA=32'h00001600; //read status register
    valueB = 32'd2;
    #10;
    start=0;
    ciN=0;
    valueA=0;
    #140;
    busyBitIn=1;
    #100;
    busyBitIn=0;
    #10000


    $finish;


end
endmodule

lab-6/virtual_prototype/modules/DMA/ramDmaCiCopy.vcd
$date
	Tue Apr 23 15:36:24 2024
$end
$version
	Icarus Verilog
$end
$timescale
	1ps
$end
$scope module dma_controller_tb $end
$var wire 32 ! addressData [31:0] $end
$var wire 1 " dataValid $end
$var wire 32 # result [31:0] $end
$var wire 1 $ requestTransaction $end
$var wire 1 % endTransaction $end
$var wire 1 & done $end
$var wire 1 ' dataValidOut $end
$var wire 4 ( byteEnable [3:0] $end
$var wire 8 ) burstSizeOut [7:0] $end
$var wire 1 * beginTransactionOut $end
$var wire 32 + addressDataOut [31:0] $end
$var parameter 8 , customIdCPU $end
$var parameter 8 - customIdDMA $end
$var reg 32 . addressDataIn [31:0] $end
$var reg 1 / beginTransactionIn $end
$var reg 1 0 busErrorIn $end
$var reg 1 1 busyBitIn $end
$var reg 8 2 ciN [7:0] $end
$var reg 1 3 clock $end
$var reg 1 4 dataValidIn $end
$var reg 1 5 endTransactionIn $end
$var reg 1 6 reset $end
$var reg 1 7 start $end
$var reg 1 8 transactionGranted $end
$var reg 32 9 valueA [31:0] $end
$var reg 32 : valueB [31:0] $end
$var integer 32 ; i [31:0] $end
$scope module uut $end
$var wire 8 < ciN [7:0] $end
$var wire 1 3 clock $end
$var wire 1 8 dmaAckBusIn $end
$var wire 32 = dmaAddressDataIn [31:0] $end
$var wire 1 0 dmaBusErrorIn $end
$var wire 1 1 dmaBusyIn $end
$var wire 1 " dmaDataValidIn $end
$var wire 1 5 dmaEndTransactionIn $end
$var wire 1 > readBlockSize $end
$var wire 1 ? readBurstSize $end
$var wire 1 @ readBusStartAddress $end
$var wire 1 A readMemoryStartAddress $end
$var wire 1 B readStatusRegister $end
$var wire 1 6 reset $end
$var wire 1 C sigBlockSize $end
$var wire 1 D sigBurstSize $end
$var wire 1 E sigBusStartAddress $end
$var wire 1 F sigMemoryStartAddress $end
$var wire 1 G sigOther $end
$var wire 1 7 start $end
$var wire 32 H valueA [31:0] $end
$var wire 32 I valueB [31:0] $end
$var wire 1 J writeAction $end
$var wire 1 K writeBlockSize $end
$var wire 1 L writeBurstSize $end
$var wire 1 M writeBusStartAddress $end
$var wire 1 N writeControlRegister $end
$var wire 1 O writeEnableA $end
$var wire 1 P writeMemoryStartAddress $end
$var wire 1 Q writeEnableB $end
$var wire 32 R ssram_outB [31:0] $end
$var wire 32 S ssram_outA [31:0] $end
$var wire 1 T s_isMyCi $end
$var wire 32 U result [31:0] $end
$var wire 1 & done $end
$var wire 1 $ dmaRequestBusOut $end
$var wire 1 V dmaReadNotWriteOut $end
$var wire 1 % dmaEndTransactionOut $end
$var wire 1 ' dmaDataValidOut $end
$var wire 32 W dmaControllerOut [31:0] $end
$var wire 4 X dmaByteEnablesOut [3:0] $end
$var wire 8 Y dmaBurstSizeOut [7:0] $end
$var wire 1 * dmaBeginTransactionOut $end
$var wire 32 Z dmaAddressDataOut [31:0] $end
$var wire 9 [ addressB [8:0] $end
$var parameter 8 \ customId $end
$var reg 32 ] dmaAddressDataIn_reg [31:0] $end
$var reg 1 ^ dmaDataValidIn_reg $end
$var reg 1 _ dmaEndTransactionIn_reg $end
$var reg 1 ` done_reg $end
$scope module DMA $end
$var wire 32 a ci_valueBIn [31:0] $end
$var wire 1 3 clock $end
$var wire 1 8 dmaAckBusIn $end
$var wire 32 b dmaAddressDataIn [31:0] $end
$var wire 8 c dmaBurstSizeOut [7:0] $end
$var wire 1 0 dmaBusErrorIn $end
$var wire 1 1 dmaBusyIn $end
$var wire 4 d dmaByteEnablesOut [3:0] $end
$var wire 1 ^ dmaDataValidIn $end
$var wire 1 _ dmaEndTransactionIn $end
$var wire 1 > readBlockSize $end
$var wire 1 ? readBurstSize $end
$var wire 1 @ readBusStartAddress $end
$var wire 1 A readMemoryStartAddress $end
$var wire 1 B readStatusRegister $end
$var wire 1 6 reset $end
$var wire 9 e ssram_addressBOut [8:0] $end
$var wire 1 K writeBlockSize $end
$var wire 1 L writeBurstSize $end
$var wire 1 M writeBusStartAddress $end
$var wire 1 N writeControlRegister $end
$var wire 1 P writeMemoryStartAddress $end
$var wire 1 Q writeEnableBOut $end
$var wire 32 f ssram_outBIn [31:0] $end
$var wire 1 $ dmaRequestBusOut $end
$var wire 1 V dmaReadNotWriteOut $end
$var wire 1 % dmaEndTransactionOut $end
$var wire 1 ' dmaDataValidOut $end
$var wire 1 * dmaBeginTransactionOut $end
$var wire 32 g dmaAddressDataOut [31:0] $end
$var wire 32 h ci_resultOut [31:0] $end
$var parameter 9 i BEGIN_TRANSACTION_READ $end
$var parameter 9 j BEGIN_TRANSACTION_WRITE $end
$var parameter 9 k END_TRANSACTION_WRITE $end
$var parameter 9 l ERROR $end
$var parameter 9 m IDLE $end
$var parameter 9 n NEW_REQUEST_WRITE $end
$var parameter 9 o READ_BURST $end
$var parameter 9 p WAIT_GRANT_READ $end
$var parameter 9 q WAIT_GRANT_WRITE $end
$var parameter 9 r WRITE_BURST $end
$var reg 10 s blockSize [9:0] $end
$var reg 8 t burstSize [7:0] $end
$var reg 8 u burstSize_counter [7:0] $end
$var reg 32 v busAddress [31:0] $end
$var reg 32 w busStartAddress [31:0] $end
$var reg 2 x control [1:0] $end
$var reg 8 y current_transaction_burstSize [7:0] $end
$var reg 32 z dmaAddressData_reg [31:0] $end
$var reg 8 { dmaBurstSize_reg [7:0] $end
$var reg 4 | dmaByteEnables_reg [3:0] $end
$var reg 9 } memoryAddress [8:0] $end
$var reg 9 ~ memoryStartAddress [8:0] $end
$var reg 10 !" resting_blockSize [9:0] $end
$var reg 32 "" result_reg [31:0] $end
$var reg 9 #" state [8:0] $end
$var reg 32 $" status [31:0] $end
$upscope $end
$scope module ssram $end
$var wire 9 %" addressA [8:0] $end
$var wire 9 &" addressB [8:0] $end
$var wire 1 3 clockA $end
$var wire 1 3 clockB $end
$var wire 32 '" dataInA [31:0] $end
$var wire 32 (" dataInB [31:0] $end
$var wire 1 O writeEnableA $end
$var wire 1 Q writeEnableB $end
$var parameter 32 )" bitwidth $end
$var parameter 32 *" nrOfEntries $end
$var parameter 32 +" readAfterWrite $end
$var reg 32 ," dataOutA [31:0] $end
$var reg 32 -" dataOutB [31:0] $end
$upscope $end
$upscope $end
$upscope $end
$enddefinitions $end
$comment Show the parameter values. $end
$dumpall
b0 +"
b1000000000 *"
b100000 )"
b11000100 r
b1000001 q
b100001 p
b10100000 o
b11110000 n
b0 m
b100110000 l
b100010000 k
b10001000 j
b1101010 i
b11111110 \
b11111110 -
b11111101 ,
$end
#0
$dumpvars
bx -"
bx ,"
b0 ("
b0 '"
b0 &"
b0 %"
b0 $"
b0 #"
b0 ""
b0 !"
b0 ~
b0 }
b0 |
b0 {
b0 z
b0 y
b0 x
b0 w
bx v
b0 u
b0 t
b0 s
b0 h
b0 g
bx f
b0 e
b0 d
b0 c
b0 b
b0 a
0`
0_
0^
b0 ]
b0 [
b0 Z
b0 Y
b0 X
b0 W
0V
b0 U
0T
bx S
bx R
0Q
0P
0O
0N
0M
0L
0K
0J
b0 I
b0 H
0G
0F
0E
0D
0C
0B
0A
0@
0?
0>
b0 =
b0 <
bx ;
b0 :
b0 9
18
07
16
05
04
03
b0 2
01
00
0/
b0 .
b0 +
0*
b0 )
b0 (
0'
0&
0%
0$
b0 #
0"
b0 !
$end
#5000
13
#10000
03
#15000
13
#20000
03
#25000
13
#30000
03
#35000
13
#40000
03
#45000
13
#50000
03
#55000
13
#60000
03
#65000
13
#70000
03
#75000
13
#80000
03
#85000
13
#90000
03
#95000
13
#100000
bx #
bx U
1&
1O
1J
1T
b1000000000 9
b1000000000 H
b0 ;
b11111110 2
b11111110 <
17
06
03
#105000
b0 #
b0 U
1`
b0 v
b0 S
b0 ,"
13
#110000
b0 R
b0 f
b0 -"
b1 %"
03
b1 :
b1 I
b1 a
b1 '"
b1000000001 9
b1000000001 H
b1 ;
#115000
b1 #
b1 U
b1 S
b1 ,"
13
#120000
b10 %"
03
b10 :
b10 I
b10 a
b10 '"
b1000000010 9
b1000000010 H
b10 ;
#125000
b10 #
b10 U
b10 S
b10 ,"
13
#130000
b11 %"
03
b11 :
b11 I
b11 a
b11 '"
b1000000011 9
b1000000011 H
b11 ;
#135000
b11 #
b11 U
b11 S
b11 ,"
13
#140000
b100 %"
03
b100 :
b100 I
b100 a
b100 '"
b1000000100 9
b1000000100 H
b100 ;
#145000
b100 #
b100 U
b100 S
b100 ,"
13
#150000
b101 %"
03
b101 :
b101 I
b101 a
b101 '"
b1000000101 9
b1000000101 H
b101 ;
#155000
b101 #
b101 U
b101 S
b101 ,"
13
#160000
b110 %"
03
b110 :
b110 I
b110 a
b110 '"
b1000000110 9
b1000000110 H
b110 ;
#165000
b110 #
b110 U
b110 S
b110 ,"
13
#170000
b111 %"
03
b111 :
b111 I
b111 a
b111 '"
b1000000111 9
b1000000111 H
b111 ;
#175000
b111 #
b111 U
b111 S
b111 ,"
13
#180000
b1000 %"
03
b1000 :
b1000 I
b1000 a
b1000 '"
b1000001000 9
b1000001000 H
b1000 ;
#185000
b1000 #
b1000 U
b1000 S
b1000 ,"
13
#190000
b1001 %"
03
b1001 :
b1001 I
b1001 a
b1001 '"
b1000001001 9
b1000001001 H
b1001 ;
#195000
b1001 #
b1001 U
b1001 S
b1001 ,"
13
#200000
b1010 %"
03
b1010 :
b1010 I
b1010 a
b1010 '"
b1000001010 9
b1000001010 H
b1010 ;
#205000
b1010 #
b1010 U
b1010 S
b1010 ,"
13
#210000
b1011 %"
03
b1011 :
b1011 I
b1011 a
b1011 '"
b1000001011 9
b1000001011 H
b1011 ;
#215000
b1011 #
b1011 U
b1011 S
b1011 ,"
13
#220000
b1100 %"
03
b1100 :
b1100 I
b1100 a
b1100 '"
b1000001100 9
b1000001100 H
b1100 ;
#225000
b1100 #
b1100 U
b1100 S
b1100 ,"
13
#230000
b1101 %"
03
b1101 :
b1101 I
b1101 a
b1101 '"
b1000001101 9
b1000001101 H
b1101 ;
#235000
b1101 #
b1101 U
b1101 S
b1101 ,"
13
#240000
b1110 %"
03
b1110 :
b1110 I
b1110 a
b1110 '"
b1000001110 9
b1000001110 H
b1110 ;
#245000
b1110 #
b1110 U
b1110 S
b1110 ,"
13
#250000
b1111 %"
03
b1111 :
b1111 I
b1111 a
b1111 '"
b1000001111 9
b1000001111 H
b1111 ;
#255000
b1111 #
b1111 U
b1111 S
b1111 ,"
13
#260000
b10000 %"
03
b10000 :
b10000 I
b10000 a
b10000 '"
b1000010000 9
b1000010000 H
b10000 ;
#265000
b10000 #
b10000 U
b10000 S
b10000 ,"
13
#270000
b10001 %"
03
b10001 :
b10001 I
b10001 a
b10001 '"
b1000010001 9
b1000010001 H
b10001 ;
#275000
b10001 #
b10001 U
b10001 S
b10001 ,"
13
#280000
b10010 %"
03
b10010 :
b10010 I
b10010 a
b10010 '"
b1000010010 9
b1000010010 H
b10010 ;
#285000
b10010 #
b10010 U
b10010 S
b10010 ,"
13
#290000
b10011 %"
03
b10011 :
b10011 I
b10011 a
b10011 '"
b1000010011 9
b1000010011 H
b10011 ;
#295000
b10011 #
b10011 U
b10011 S
b10011 ,"
13
#300000
b10100 %"
03
b10100 :
b10100 I
b10100 a
b10100 '"
b1000010100 9
b1000010100 H
b10100 ;
#305000
b10100 #
b10100 U
b10100 S
b10100 ,"
13
#310000
b10101 %"
03
b10101 :
b10101 I
b10101 a
b10101 '"
b1000010101 9
b1000010101 H
b10101 ;
#315000
b10101 #
b10101 U
b10101 S
b10101 ,"
13
