lab-5/virtual_prototype/modules/DMA/DMAController.v
module DMAController (
    input wire validInstruction, writeEnable, clock, reset,
    input wire[2:0] configurationBits,
    output wire[31:0] readSettings,
    input wire[31:0] writeSettings,
    output wire[1:0] status,

    //memory ports
    output wire[8:0] memAddress,
    input wire[31:0] memDataIn,
    output wire[31:0] memDataOut,
    output wire memWriteEnable, 

    //bus ports
    input wire[31:0] address_data_in,
    output wire[31:0] address_data_out,
    output wire[3:0] byte_enables_out,
    output wire[7:0] burst_size_out,
    output wire read_n_write_out, begin_transaction_out, end_transaction_out, data_valid_out,
    input wire end_transaction_in, data_valid_in, busy_in, error_in,
    input wire grantRequest,
    output wire busRequest
);

    reg[2:0] state;     // modification
    localparam IDLE = 3'd0;
    parameter REQUEST = 3'd1;
    localparam INIT = 3'd2;
    parameter READ = 3'd3;
    parameter CLOSE = 3'd4;
    parameter WRITE = 3'd5;
    parameter C2R = 3'd6;
    
    reg[31:0] busStart;
    reg[8:0] memoryStart;
    reg[9:0] blockSize;
    reg[8:0] burstSize;
    reg[1:0] statusRegister;
    reg[1:0] controlRegister;

    reg[31:0] busAddress; 
    reg[8:0] memAddress_r;
    reg[8:0] burstCounter;
    reg[9:0] blockCounter;
    
    reg[9:0] blockCounterCurr; // modification

    reg[0:2] memCounter = 3'b0;

    //CPU

    assign readSettings = (validInstruction == 0) ? 32'b0 : 
                            (configurationBits == 3'b001) ? busStart : 
                                (configurationBits == 3'b010) ? memoryStart : 
                                    (configurationBits == 3'b011) ? blockSize :
                                        (configurationBits == 3'b100) ? burstSize :
                                            (configurationBits == 3'b101) ? statusRegister : 32'b0; 

    assign status = statusRegister;
    
    always @(posedge clock) begin
        if(reset == 1) begin
            busStart <= 0; 
            memoryStart <= 0; //c'era scritto memory. Corretto a memory start
            blockSize <= 0;
            burstSize <= 0;
            statusRegister <= 0;
            controlRegister <= 0;
        end else if(validInstruction == 1 && writeEnable == 1) begin
            case (configurationBits)
                3'd1: begin  busStart <= writeSettings; end
                3'd2: begin  memoryStart <= writeSettings[8:0]; end
                3'd3: begin  blockSize <= writeSettings[9:0]; end
                3'd4: begin burstSize <= writeSettings[7:0] + 1; end
                3'd5: begin controlRegister <= writeSettings[1:0]; end//set operation
                default: begin end//not so sure
            endcase
        end
    end

    // MEMORY

    assign memAddress = memAddress_r;
    assign memWriteEnable = (state == READ && data_valid_in == 1'b1) ? 1'b1 : 1'b0;
    assign memDataOut = address_data_in;

    always @(posedge clock) begin
        if(reset == 1) begin 
            memAddress_r <= 9'b0;
        end else if((state == READ || state == WRITE) && data_valid_in == 1) begin
            memAddress_r <= memAddress_r + 1;
        end else if (state == INIT) begin
            memAddress_r <= memoryStart;
        end else begin
            memAddress_r <= memAddress_r;
        end
    end

    // BUS

    assign busRequest = (state == REQUEST) ? 1'b1 : 1'b0;

    assign begin_transaction_out = (state == INIT) ? 1'b1 : 1'b0;
    assign read_n_write_out = (state == INIT) ? (controlRegister[0] == 1) ? 1'b1 : 1'b0 : 1'b0;
    assign address_data_out = (state == INIT) ? busAddress : (state == WRITE) ? memDataIn: 32'b0; 
    assign burst_size_out = (state == INIT) ? (blockSize - blockCounterCurr) < burstSize ? (blockSize - blockCounterCurr) : burstSize[7:0] : 8'b0;  // possibile soluzione con sottrazione, comparator e mux
    
    assign data_valid_out = (state == WRITE && memCounter[2] == 1'b1 && !busy_in) ? 1'b1 : 1'b0;

    assign end_transaction_out = (state == CLOSE || state == C2R) ? 1'b1 : 1'b0;

    always @(posedge clock) begin
        if (reset == 1) begin 
            memCounter <= 3'b0;
        end else if(state == WRITE && !busy_in) begin
            memCounter <= (memCounter == 2'd2) ? 0 : memCounter + 1;
        end else if(state == INIT) begin
            memCounter <= 0;
        end else begin
            memCounter <= memCounter;
        end
    end

    always @(posedge clock) begin
        if(reset == 1) begin
            burstCounter <= 9'b0;
            blockCounter <= 10'b0;
            blockCounterCurr <= 10'b0;
            busAddress <= 32'b0;
        end else if((state == READ || state == WRITE) && data_valid_in == 1) begin  // maybe only put data valid to not lose a clk cycle
            burstCounter <= burstCounter + 1;                                       
            blockCounter <= blockCounter + 1;                                       
            blockCounterCurr <= blockCounterCurr + 1;
            busAddress <= busAddress + 4; //byte addressable
        end else if (state == INIT) begin
            burstCounter <= 9'b0;
            blockCounter <= 10'b0;
            busAddress <= busStart;
        end else begin
            blockCounterCurr <= blockCounterCurr;
            burstCounter <= burstCounter;
            blockCounter <= blockCounter;
            busAddress <= busAddress;
        end
    end

    // FSM ( TO DO: migliorare gestione status e control register)

    always @(posedge clock) begin
        if (reset == 1) begin
            state <= IDLE;
        end else begin
            case (state)
                IDLE: begin
                    if (controlRegister[0] != controlRegister[1]) begin
                        statusRegister <= 2'd1; 
                        state <= REQUEST;
                    end else begin
                        statusRegister[0] <= 1'b0; 
                        state <= IDLE;
                    end
                end
                REQUEST: begin
                    if(grantRequest == 1) begin 
                        state <= INIT;
                    end else begin
                        state <= REQUEST;
                    end
                end
                INIT: begin
                    controlRegister <= 2'b0;
                    state <= READ;
                
                end
                READ: begin
                    if(error_in == 1) begin 
                        statusRegister[1] <= 1'b1;
                        state <= CLOSE;
                    end else if (end_transaction_in == 1) begin 
                        if (blockCounter == blockSize) begin
                            statusRegister[0] <= 1'b0;
                            state <= IDLE;
                        end else begin
                            state <= REQUEST;
                        end
                    end else begin
                        state <= READ;
                    end
                end
                WRITE: begin
                    if(error_in == 1) begin 
                        statusRegister[1] <= 1'b1;
                        state <= CLOSE;
                    end else if (blockCounter == blockSize) begin
                        statusRegister[0] <= 1'b0;
                        state <= CLOSE;
                    end else if (burstCounter == burstSize) begin
                        state <= C2R;
                    end else begin
                        state <= WRITE;
                    end    
                end
                C2R: begin
                   state <= REQUEST; 
                end
                CLOSE: begin
                    statusRegister[0] <= 1'b0;
                    state <= IDLE;
                end
                default: begin
                    statusRegister[0] <= 1'b0; 
                    state <= IDLE;
                end
            endcase
        end
    end
    
endmodule

lab-5/virtual_prototype/modules/DMA/dualPortSSRAM.v
module dualPortSSRAM #( parameter bitwidth = 8, parameter nrOfEntries = 512, parameter readAfterWrite = 0 )
( 
    input wire clockA, clockB, writeEnableA, writeEnableB,
    input wire [$clog2(nrOfEntries)-1 : 0] addressA, addressB,
    input wire [bitwidth-1 : 0] dataInA, dataInB,
    output reg [bitwidth-1 : 0] dataOutA, dataOutB
);

    reg [bitwidth-1 : 0] memoryContent [nrOfEntries-1 : 0];

    always @(posedge clockA) begin
        if (readAfterWrite != 0) dataOutA = memoryContent[addressA];
        if (writeEnableA == 1'b1) memoryContent[addressA] = dataInA;
        if (readAfterWrite == 0) dataOutA = memoryContent[addressA];
    end

    always @(posedge clockB) begin
        if (readAfterWrite != 0) dataOutB = memoryContent[addressB];
        if (writeEnableB == 1'b1) memoryContent[addressB] = dataInB;
        if (readAfterWrite == 0) dataOutB = memoryContent[addressB];
    end

endmodule

lab-5/virtual_prototype/modules/DMA/ramDmaCi.v
module ramDmaCi #(
    parameter[7:0] customId = 8'h00
) (
    input wire      start,
                    clock,
                    reset,
    input wire[31:0] valueA, valueB,
    input wire[7:0] ciN,
    output wire done, 
    output wire[31:0] result,

    //bus ports
    input wire[31:0] address_data_in,
    output wire[31:0] address_data_out,
    output wire[3:0] byte_enables_out,
    output wire[7:0] burst_size_out,
    output wire read_n_write_out, begin_transaction_out, end_transaction_out, data_valid_out,
    input wire end_transaction_in, data_valid_in, busy_in, error_in,
    input wire grantRequest,
    output wire busRequest
);

    reg[1:0] counter;

    wire is_valid, is_memory;
    wire[1:0] status;

    wire[31:0] dataOutA, resultMem, resultDMA;
    wire doneMem, doneDMA;

    wire[8:0] memAddress;
    wire[31:0] memDataIn, memDataOut;
    wire memWriteEnable;

    assign doneDMA = (is_valid == 1'b1 && ~is_memory) ? 1'b1 : 1'b0;
    assign doneMem = (is_valid == 1'b1 && is_memory && (counter == 2'd2 || valueA[9] == 1'b1) )? 1'b1 : 1'b0;

    assign resultMem = (is_valid == 1'b1 && is_memory) ? dataOutA : 32'b0;

    assign done = doneDMA | doneMem;
    assign result = resultMem | resultDMA;

    assign is_valid = (ciN == customId && start == 1'b1);
    assign is_memory = (valueA[12:10] == 3'b0);

    // modification: logic for counter
    always@(posedge clock) begin
        if(reset == 1'b1) begin
            counter = 0;
        end else begin
            counter <= (counter == 2'd2 || !is_valid || valueA[9] == 1'b0) ? 2'd0 : counter + 1;
        end

    end

    dualPortSSRAM #(.bitwidth(32), .nrOfEntries(512), .readAfterWrite(0)) memory(
        .clockA(clock),
        .clockB(~clock),
        .writeEnableA(is_valid && valueA[9] && is_memory),
        .writeEnableB(memWriteEnable),
        .addressA(valueA[8:0]),
        .addressB(memAddress),
        .dataInA(valueB),
        .dataInB(memDataOut),
        .dataOutA(dataOutA),
        .dataOutB(memDataIn)
    );

    DMAController dmaController(
        .validInstruction(is_valid),
        .writeEnable(valueA[9]),
        .clock(clock),
        .reset(reset),
        .configurationBits(valueA[12:10]),
        .readSettings(resultDMA),
        .writeSettings(valueB),
        .status(status),

        .memAddress(memAddress),
        .memDataIn(memDataIn),
        .memDataOut(memDataOut),
        .memWriteEnable(memWriteEnable),

        //bus ports
    .address_data_in(address_data_in),
    .address_data_out(address_data_out),
    .byte_enables_out(byte_enables_out),
    .burst_size_out(burst_size_out),
    .read_n_write_out(read_n_write_out), 
    .begin_transaction_out(begin_transaction_out), 
    .end_transaction_out(end_transaction_out), 
    .data_valid_out(data_valid_out),
    .end_transaction_in(end_transaction_in), 
    .data_valid_in(data_valid_in), 
    .busy_in(busy_in), 
    .error_in(error_in),
    .grantRequest(grantRequest),
    .busRequest(busRequest)
    );
    
endmodule

lab-5/virtual_prototype/modules/DMA/ramDmaCi_tb.v


module ramDmaCi_tb;

    // define input/inout tb signals
    reg clock, reset, start;
    reg[31:0] valueA, valueB;
    reg[7:0] CiN;
    reg[31:0] address_data_in;
    reg data_valid_in, end_transaction_in;
    reg grantRequest;
 
    // define out signals as wires
    wire done;
    wire[31:0] result;
    wire[31:0] address_data_out;
    wire[3:0]  byte_enables_out;
    wire[7:0]  burst_size_out;
    wire begin_transaction_out, data_valid_out, end_transaction_out,
         read_n_write_out, busy_in, error_in;
    wire busRequest;
    
    // instantiate component
    ramDmaCi #(.customId(8'd27)) dut
        (
            .reset(reset),
            .clock(clock),
            .start(start),
            .valueA(valueA),
            .valueB(valueB),
            .ciN(CiN),
            .address_data_in(address_data_in),  // no need to do the or beacuse, in this simulation, only one slave talks to the dma
            .address_data_out(address_data_out),
            .byte_enables_out(byte_enables_out),
            .burst_size_out(burst_size_out),
            .read_n_write_out(read_n_write_out),
            .begin_transaction_out(begin_transaction_out),
            .end_transaction_in(end_transaction_in),
            .end_transaction_out(end_transaction_out),
            .data_valid_in(data_valid_in),
            .data_valid_out(data_valid_out),
            .busy_in(busy_in),
            .error_in(error_in),
            .done(done),
            .result(result),
            .grantRequest(grantRequest),
            .busRequest(busRequest)
        );

    // Set the rst to 1. keep the rst to 1 for 4 cycles. Set the reset to 0. Start "forever" with the clock
    initial
    begin
        reset = 1'b1;
        clock = 1'b0;
        repeat (4) #5 clock = ~clock;
        reset = 1'b0;
        forever #5 clock = ~clock;
    end

    initial
    begin

        // set CiN to the custom instruction and start to 1
        start = 1;
        CiN = 8'd27;
        grantRequest = 1'b1;

        // Configurations:
        // set the Block size
        valueA[9] = 1;
        valueA[12:10] = 3'd3;
        valueB[9:0] = 10'd5;
        data_valid_in = 1'b0;
        address_data_in = 32'b0;
        end_transaction_in = 1'b0; 
        repeat(3) @(negedge clock);

        // set the burst size
        valueA[12:10] = 3'd4;
        valueB[7:0] = 3'd1; // busrtSize = 2;
        repeat(3) @(negedge clock);

        // set the memory base address
        valueA[12:10] = 3'd2;
        valueB[8:0] = 9'b0;
        repeat(3) @(negedge clock);

        // set the bus base address
        valueA[12:10] = 3'd1;
        valueB[31:0] = 32'd0;
        repeat(3) @(negedge clock);

        // set the control reg to initialize a writing into the CiMem
        valueA[12:10] = 3'd5;
        valueB[1:0] = 1'd1;
        repeat(3) @(negedge clock);
        valueA[31:0] = 32'b0;
        valueB[31:0] = 32'b0;
        repeat(1) @(posedge clock);

        // start sending data to the dma
        data_valid_in = 1'b1; // driven by two drives. In DMAController is set to zero.
        address_data_in = 32'd1;
        repeat(1) @(posedge clock);
        address_data_in = 32'd2;
        repeat(1) @(posedge clock);

        data_valid_in = 1'b0;
        end_transaction_in = 1'b1;
        repeat(1) @(posedge clock);
        end_transaction_in = 1'b0;
        repeat(1) @(posedge clock);

        data_valid_in = 1'b1;
        address_data_in = 32'd3;
        repeat(1) @(posedge clock);
        address_data_in = 32'd4;
        repeat(1) @(posedge clock);

        data_valid_in = 1'b0;
        end_transaction_in = 1'b1;
        repeat(1) @(posedge clock);
        end_transaction_in = 1'b0;
        repeat(1) @(posedge clock);

        data_valid_in = 1'b1;
        address_data_in = 32'd5;
        repeat(1) @(posedge clock);

        data_valid_in = 1'b0;
        end_transaction_in = 1'b1;
        repeat(1) @(posedge clock);
        end_transaction_in = 1'b0;
        repeat(3) @(negedge clock);
        
        // set start to zero
        start = 1'b0;
        repeat(3) @(negedge clock);
        $finish;

    end

initial 
begin
    $dumpfile("ramDmaCi.vcd");
    $dumpvars(0, dut);
end
endmodule

lab-5/virtual_prototype/modules/DMA/ramDmaCi.vcd
$date
	Tue Apr 16 09:59:09 2024
$end
$version
	Icarus Verilog
$end
$timescale
	1s
$end
$scope module ramDmaCi_tb $end
$scope module dut $end
$var wire 32 ! address_data_in [31:0] $end
$var wire 1 " busy_in $end
$var wire 4 # byte_enables_out [3:0] $end
$var wire 8 $ ciN [7:0] $end
$var wire 1 % clock $end
$var wire 1 & data_valid_in $end
$var wire 1 ' done $end
$var wire 1 ( end_transaction_in $end
$var wire 1 ) error_in $end
$var wire 1 * grantRequest $end
$var wire 1 + is_valid $end
$var wire 1 , reset $end
$var wire 32 - result [31:0] $end
$var wire 1 . start $end
$var wire 32 / valueA [31:0] $end
$var wire 32 0 valueB [31:0] $end
$var wire 2 1 status [1:0] $end
$var wire 32 2 resultMem [31:0] $end
$var wire 32 3 resultDMA [31:0] $end
$var wire 1 4 read_n_write_out $end
$var wire 1 5 memWriteEnable $end
$var wire 32 6 memDataOut [31:0] $end
$var wire 32 7 memDataIn [31:0] $end
$var wire 9 8 memAddress [8:0] $end
$var wire 1 9 is_memory $end
$var wire 1 : end_transaction_out $end
$var wire 1 ; doneMem $end
$var wire 1 < doneDMA $end
$var wire 1 = data_valid_out $end
$var wire 32 > dataOutA [31:0] $end
$var wire 1 ? busRequest $end
$var wire 8 @ burst_size_out [7:0] $end
$var wire 1 A begin_transaction_out $end
$var wire 32 B address_data_out [31:0] $end
$var parameter 8 C customId $end
$var reg 2 D counter [1:0] $end
$scope module dmaController $end
$var wire 32 E address_data_in [31:0] $end
$var wire 1 " busy_in $end
$var wire 4 F byte_enables_out [3:0] $end
$var wire 1 % clock $end
$var wire 3 G configurationBits [2:0] $end
$var wire 1 & data_valid_in $end
$var wire 1 ( end_transaction_in $end
$var wire 1 ) error_in $end
$var wire 1 * grantRequest $end
$var wire 9 H memAddress [8:0] $end
$var wire 32 I memDataOut [31:0] $end
$var wire 1 , reset $end
$var wire 2 J status [1:0] $end
$var wire 1 + validInstruction $end
$var wire 1 K writeEnable $end
$var wire 32 L writeSettings [31:0] $end
$var wire 1 4 read_n_write_out $end
$var wire 32 M readSettings [31:0] $end
$var wire 1 5 memWriteEnable $end
$var wire 32 N memDataIn [31:0] $end
$var wire 1 : end_transaction_out $end
$var wire 1 = data_valid_out $end
$var wire 1 ? busRequest $end
$var wire 8 O burst_size_out [7:0] $end
$var wire 1 A begin_transaction_out $end
$var wire 32 P address_data_out [31:0] $end
$var parameter 3 Q C2R $end
$var parameter 3 R CLOSE $end
$var parameter 3 S IDLE $end
$var parameter 3 T INIT $end
$var parameter 3 U READ $end
$var parameter 3 V REQUEST $end
$var parameter 3 W WRITE $end
$var reg 10 X blockCounter [9:0] $end
$var reg 10 Y blockCounterCurr [9:0] $end
$var reg 10 Z blockSize [9:0] $end
$var reg 9 [ burstCounter [8:0] $end
$var reg 9 \ burstSize [8:0] $end
$var reg 32 ] busAddress [31:0] $end
$var reg 32 ^ busStart [31:0] $end
$var reg 2 _ controlRegister [1:0] $end
$var reg 9 ` memAddress_r [8:0] $end
$var reg 3 a memCounter [0:2] $end
$var reg 9 b memoryStart [8:0] $end
$var reg 3 c state [2:0] $end
$var reg 2 d statusRegister [1:0] $end
$upscope $end
$scope module memory $end
$var wire 9 e addressA [8:0] $end
$var wire 9 f addressB [8:0] $end
$var wire 1 % clockA $end
$var wire 1 g clockB $end
$var wire 32 h dataInA [31:0] $end
$var wire 32 i dataInB [31:0] $end
$var wire 1 j writeEnableA $end
$var wire 1 5 writeEnableB $end
$var parameter 32 k bitwidth $end
$var parameter 32 l nrOfEntries $end
$var parameter 32 m readAfterWrite $end
$var reg 32 n dataOutA [31:0] $end
$var reg 32 o dataOutB [31:0] $end
$upscope $end
$upscope $end
$upscope $end
$enddefinitions $end
$comment Show the parameter values. $end
$dumpall
b0 m
b1000000000 l
b100000 k
b101 W
b1 V
b11 U
b10 T
b0 S
b100 R
b110 Q
b11011 C
$end
#0
$dumpvars
bx o
bx n
0j
b0 i
bx0000000101 h
1g
bx f
bx e
bx d
bx c
bx b
b0 a
bx `
bx _
bx ^
bx ]
bx \
bx [
bx Z
bx Y
bx X
bx P
bx O
bx N
b0xxxxxxxxxx M
bx0000000101 L
1K
bx J
b0 I
bx H
b11 G
bz F
b0 E
bx D
bx B
xA
bx @
x?
bx >
0=
1<
0;
x:
09
bx 8
bx 7
b0 6
05
x4
b0xxxxxxxxxx 3
b0 2
bx 1
bx0000000101 0
bx0111xxxxxxxxx /
1.
b0xxxxxxxxxx -
1,
1+
1*
z)
0(
1'
0&
0%
b11011 $
bz #
z"
b0 !
$end
#5
b0 -
b0 3
b0 M
b0 @
b0 O
0:
0?
0A
04
b0 B
b0 P
b0 _
b0 1
b0 J
b0 d
b0 \
b0 Z
b0 b
b0 ^
b0 8
b0 H
b0 f
b0 `
b0 ]
b0 Y
b0 X
b0 [
b0 c
0g
b0 D
1%
#10
1g
0%
#15
0g
1%
#20
1g
0,
0%
#25
b101 -
b101 3
b101 M
b101 Z
b1 D
0g
1%
#30
b0 -
b0 3
b0 M
b100 G
1g
bx0000000001 0
bx0000000001 L
bx0000000001 h
bx1001xxxxxxxxx /
0%
#35
b10 -
b10 3
b10 M
b10 D
b10 \
0g
1%
#40
1g
0%
#45
b0 D
0g
1%
#50
1g
0%
#55
b1 D
0g
1%
#60
b0 -
b0 3
b0 M
b10 G
1g
bx0000000000 0
bx0000000000 L
bx0000000000 h
bx0101xxxxxxxxx /
0%
#65
b10 D
0g
1%
#70
1g
0%
#75
b0 D
0g
1%
#80
1g
0%
#85
b1 D
0g
1%
#90
b1 G
1g
b0 0
b0 L
b0 h
bx0011xxxxxxxxx /
0%
#95
b10 D
0g
1%
#100
1g
0%
#105
b0 D
0g
1%
#110
1g
0%
#115
b1 D
0g
1%
#120
b101 G
1g
b1 0
b1 L
b1 h
bx1011xxxxxxxxx /
0%
#125
b1 _
b10 D
0g
1%
#130
1g
0%
#135
b1 -
b1 3
b1 M
1?
b0 D
b1 c
b1 1
b1 J
b1 d
0g
1%
#140
1g
0%
#145
b10 @
b10 O
0?
1A
14
b10 c
b1 D
0g
1%
#150
b0 3
b0 M
0'
bx -
0;
0<
bx 2
19
b0 e
0K
b0 G
1g
b0 0
b0 L
b0 h
b0 /
0%
#155
15
b0 @
b0 O
0A
04
b0 D
b11 c
b0 _
0g
b1 6
b1 I
b1 i
b1 !
b1 E
1&
1%
#160
b1 7
b1 N
b1 o
1g
0%
#165
b1 8
b1 H
b1 f
b1 `
b100 ]
b1 Y
b1 X
b1 [
b1 -
b1 2
0g
b10 6
b10 I
b10 i
b10 !
b10 E
b1 >
b1 n
1%
#170
b10 7
b10 N
b10 o
1g
0%
#175
1?
b1 c
05
0g
1(
0&
1%
#180
1g
0%
#185
b10 @
b10 O
0?
1A
b100 B
b100 P
b10 c
0g
0(
1%
#190
1g
0%
#195
15
b0 @
b0 O
0A
b0 B
b0 P
b11 c
b0 ]
b0 X
b0 [
b0 8
b0 H
b0 f
b0 `
0g
b11 6
b11 I
b11 i
b11 !
b11 E
1&
1%
#200
b11 7
b11 N
b11 o
1g
0%
#205
b1 8
b1 H
b1 f
b1 `
b100 ]
b10 Y
b1 X
b1 [
b11 -
b11 2
0g
b100 6
b100 I
b100 i
b100 !
b100 E
b11 >
b11 n
1%
#210
b100 7
b100 N
b100 o
1g
0%
#215
1?
b1 c
05
0g
1(
0&
1%
#220
1g
0%
#225
b10 @
b10 O
0?
1A
b100 B
b100 P
b10 c
0g
0(
1%
#230
1g
0%
#235
15
b0 @
b0 O
0A
b0 B
b0 P
b11 c
b0 ]
b0 X
b0 [
b0 8
b0 H
b0 f
b0 `
0g
b101 6
b101 I
b101 i
b101 !
b101 E
1&
1%
#240
b101 7
b101 N
b101 o
1g
0%
#245
b1 8
b1 H
b1 f
b1 `
b100 ]
b11 Y
b1 X
b1 [
05
b101 -
b101 2
0g
1(
0&
b101 >
b101 n
1%
#250
b100 7
b100 N
b100 o
1g
0%
#255
0g
0(
1%
#260
1g
0%
#265
0g
1%
#270
1g
0%
#275
0g
1%
#280
b0 -
b0 2
0+
1g
0.
0%
