lab-5/virtual_prototype/modules/DMA/DMAController.v
module DMAController (
    input wire validInstruction, writeEnable, clock, reset,
    input wire[2:0] configurationBits,
    output wire[31:0] readSettings,
    input wire[31:0] writeSettings,
    output wire[1:0] status,

    //memory ports
    output wire[8:0] memAddress,
    input wire[31:0] memDataIn,
    output wire[31:0] memDataOut,
    output wire memWriteEnable, 

    //bus ports
    inout wire[31:0] address_data,
    inout wire[3:0] byte_enables,
    inout wire[7:0] burst_size,
    inout wire read_n_write, begin_transaction, end_transaction, data_valid, busy, error,
    input wire grantRequest,
    output wire busRequest
);

    reg[2:0] state;     // modification
    localparam IDLE = 3'd0;
    parameter REQUEST = 3'd1;
    localparam INIT = 3'd2;
    parameter READ = 3'd3;
    parameter CLOSE = 3'd4;
    parameter WRITE = 3'd5;
    parameter C2R = 3'd6;
    
    reg[31:0] busStart;
    reg[8:0] memoryStart;
    reg[9:0] blockSize;
    reg[8:0] burstSize;
    reg[1:0] statusRegister;
    reg[1:0] controlRegister;

    reg[31:0] busAddress; 
    reg[8:0] memAddress_r;
    reg[8:0] burstCounter;
    reg[9:0] blockCounter;
    
    reg[9:0] blockCounterCurr; // modification

    reg[0:2] memCounter = 3'b0;

    //CPU

    assign readSettings = (validInstruction == 0) ? 32'b0 : 
                            (configurationBits == 3'b001) ? busStart : 
                                (configurationBits == 3'b010) ? memoryStart : 
                                    (configurationBits == 3'b011) ? blockSize :
                                        (configurationBits == 3'b100) ? burstSize :
                                            (configurationBits == 3'b101) ? statusRegister : 32'b0; 

    assign status = statusRegister;
    
    always @(posedge clock) begin
        if(reset == 1) begin
            busStart <= 0; 
            memoryStart <= 0; //c'era scritto memory. Corretto a memory start
            blockSize <= 0;
            burstSize <= 0;
            statusRegister <= 0;
            controlRegister <= 0;
        end else if(validInstruction == 1 && writeEnable == 1) begin
            case (configurationBits)
                3'd1: begin  busStart <= writeSettings; end
                3'd2: begin  memoryStart <= writeSettings[8:0]; end
                3'd3: begin  blockSize <= writeSettings[9:0]; end
                3'd4: begin burstSize <= writeSettings[7:0] + 1; end
                3'd5: begin controlRegister <= writeSettings[1:0]; end//set operation
                default: begin end//not so sure
            endcase
        end
    end

    // MEMORY

    assign memAddress = memAddress_r;
    assign memWriteEnable = (state == READ && data_valid == 1'b1) ? 1'b1 : 1'b0;
    assign memDataOut = address_data;

    always @(posedge clock) begin
        if(reset == 1) begin 
            memAddress_r <= 9'b0;
        end else if((state == READ || state == WRITE) && data_valid == 1) begin
            memAddress_r <= memAddress_r + 1;
        end else if (state == INIT) begin
            memAddress_r <= memoryStart;
        end else begin
            memAddress_r <= memAddress_r;
        end
    end

    // BUS

    assign busRequest = (state == REQUEST) ? 1'b1 : 1'b0;

    assign begin_transaction = (state == INIT) ? 1'b1 : 1'b0;
    assign read_n_write = (state == INIT) ? (controlRegister[0] == 1) ? 1'b1 : 1'b0 : 1'b0;
    assign address_data = (state == INIT) ? busAddress : (state == WRITE) ? memDataIn: 32'b0; 
    assign burst_size = (state == INIT) ? (blockSize - blockCounterCurr) < burstSize ? (blockSize - blockCounterCurr) : burstSize[7:0] : 8'b0;  // possibile soluzione con sottrazione, comparator e mux
    
    assign data_valid = (state == WRITE && memCounter[2] == 1'b1 && !busy) ? 1'b1 : 1'b0;

    assign end_transaction = (state == CLOSE || state == C2R) ? 1'b1 : 1'b0;

    always @(posedge clock) begin
        if (reset == 1) begin 
            memCounter <= 3'b0;
        end else if(state == WRITE && !busy) begin
            memCounter <= (memCounter == 2'd2) ? 0 : memCounter + 1;
        end else if(state == INIT) begin
            memCounter <= 0;
        end else begin
            memCounter <= memCounter;
        end
    end

    always @(posedge clock) begin
        if(reset == 1) begin
            burstCounter <= 9'b0;
            blockCounter <= 10'b0;
            busAddress <= 32'b0;
        end else if((state == READ || state == WRITE) && data_valid == 1) begin
            burstCounter <= burstCounter + 1;
            blockCounter <= blockCounter + 1;
            busAddress <= busAddress + 4; //byte addressable
        end else if (state == INIT) begin
            // modification
            blockCounterCurr <= blockCounter;
            burstCounter <= 9'b0;
            blockCounter <= 10'b0;
            busAddress <= busStart;
        end else begin
            burstCounter <= burstCounter;
            blockCounter <= blockCounter;
            busAddress <= busAddress;
        end
    end

    // FSM ( TO DO: migliorare gestione status e control register)

    always @(posedge clock) begin
        if (reset == 1) begin
            state <= IDLE;
        end else begin
            case (state)
                IDLE: begin
                    if (controlRegister[0] != controlRegister[1]) begin
                        statusRegister <= 2'd1; 
                        state <= REQUEST;
                    end else begin
                        statusRegister[0] <= 1'b0; 
                        state <= IDLE;
                    end
                end
                REQUEST: begin
                    if(grantRequest == 1) begin 
                        state <= INIT;
                    end else begin
                        state <= REQUEST;
                    end
                end
                INIT: begin
                    controlRegister <= 2'b0;
                    state <= READ;
                end
                READ: begin
                    if(error == 1) begin 
                        statusRegister[1] <= 1'b1;
                        state <= CLOSE;
                    end else if (end_transaction == 1) begin 
                        if (blockCounter == blockSize) begin
                            statusRegister[0] <= 1'b0;
                            state <= IDLE;
                        end else begin
                            state <= REQUEST;
                        end
                    end else begin
                        state <= READ;
                    end
                end
                WRITE: begin
                    if(error == 1) begin 
                        statusRegister[1] <= 1'b1;
                        state <= CLOSE;
                    end else if (blockCounter == blockSize) begin
                        statusRegister[0] <= 1'b0;
                        state <= CLOSE;
                    end else if (burstCounter == burstSize) begin
                        state <= C2R;
                    end else begin
                        state <= WRITE;
                    end    
                end
                C2R: begin
                   state <= REQUEST; 
                end
                CLOSE: begin
                    statusRegister[0] <= 1'b0;
                    state <= IDLE;
                end
                default: begin
                    statusRegister[0] <= 1'b0; 
                    state <= IDLE;
                end
            endcase
        end
    end
    
endmodule

lab-5/virtual_prototype/modules/DMA/dualPortSSRAM.v
module dualPortSSRAM #( parameter bitwidth = 8, parameter nrOfEntries = 512, parameter readAfterWrite = 0 )
( 
    input wire clockA, clockB, writeEnableA, writeEnableB,
    input wire [$clog2(nrOfEntries)-1 : 0] addressA, addressB,
    input wire [bitwidth-1 : 0] dataInA, dataInB,
    output reg [bitwidth-1 : 0] dataOutA, dataOutB
);

    reg [bitwidth-1 : 0] memoryContent [nrOfEntries-1 : 0];

    always @(posedge clockA) begin
        if (readAfterWrite != 0) dataOutA = memoryContent[addressA];
        if (writeEnableA == 1'b1) memoryContent[addressA] = dataInA;
        if (readAfterWrite == 0) dataOutA = memoryContent[addressA];
    end

    always @(posedge clockB) begin
        if (readAfterWrite != 0) dataOutB = memoryContent[addressB];
        if (writeEnableB == 1'b1) memoryContent[addressB] = dataInB;
        if (readAfterWrite == 0) dataOutB = memoryContent[addressB];
    end

endmodule

lab-5/virtual_prototype/modules/DMA/ramDmaCi.v
module ramDmaCi #(
    parameter[7:0] customId = 8'h00
) (
    input wire      start,
                    clock,
                    reset,
    input wire[31:0] valueA, valueB,
    input wire[7:0] ciN,
    output wire done, 
    output wire[31:0] result,

    //bus ports
    inout wire[31:0] address_data,
    inout wire[3:0] byte_enables,
    inout wire[7:0] burst_size,
    inout wire read_n_write, begin_transaction, end_transaction, data_valid, busy, error
);

    reg[1:0] counter; // modification

    wire is_valid, is_memory;
    wire[1:0] status;

    wire[31:0] dataOutA, resultMem, resultDMA;
    wire doneMem, doneDMA;

    wire[8:0] memAddress;
    wire[31:0] memDataIn, memDataOut;
    wire memWriteEnable;

    assign doneDMA = (is_valid == 1'b1 && ~is_memory) ? 1'b1 : 1'b0;
    assign doneMem = (is_valid == 1'b1 && is_memory && (counter == 2'd2 || valueA[9] == 1'b1) )? 1'b1 : 1'b0; //se scrittura subito up altrimenti dopo due clock

    assign resultMem = (is_valid == 1'b1 && is_memory) ? dataOutA : 32'b0;

    assign done = doneDMA | doneMem;
    assign result = resultMem | resultDMA;

    assign is_valid = (ciN == customId && start == 1'b1);
    assign is_memory = (valueA[12:10] == 3'b0);

    // modification: logic for counter
    always@(posedge clock) begin
        if(reset == 1'b1) begin
            counter = 0;
        end else begin
            counter <= (counter == 2'd2) ? 2'd0 : counter + 1;
        end

    end

    dualPortSSRAM #(.bitwidth(32), .nrOfEntries(512), .readAfterWrite(0)) memory(
        .clockA(clock),
        .clockB(~clock),
        .writeEnableA(is_valid && valueA[9] && is_memory),
        .writeEnableB(memWriteEnable),
        .addressA(valueA[8:0]),
        .addressB(memAddress),
        .dataInA(valueB),
        .dataInB(memDataOut),
        .dataOutA(dataOutA),
        .dataOutB(memDataIn)
    );

    DMAController dmaController(
        .validInstruction(is_valid),
        .writeEnable(valueA[9]),
        .clock(clock),
        .reset(reset),
        .configurationBits(valueA[12:10]),
        .readSettings(resultDMA),
        .writeSettings(valueB),
        .status(status),

        .memAddress(memAddress),
        .memDataIn(memDataIn),
        .memDataOut(memDataOut),
        .memWriteEnable(memWriteEnable),

        .address_data(address_data),
        .byte_enables(byte_enables),
        .burst_size(burst_size),
        .read_n_write(read_n_write),
        .begin_transaction(begin_transaction),
        .end_transaction(end_transaction),
        .data_valid(data_valid),
        .busy(busy),
        .error(error)
    );
    
endmodule

lab-5/virtual_prototype/modules/DMA/ramDmaCi_tb.v


module ramDmaCi_tb;

    // define input/inout tb signals
    reg clock, reset, start;
    reg[31:0] valueA, valueB;
    reg[7:0] CiN;
    wire[31:0] address_data;
    wire[3:0] byte_enables;
    wire[7:0] burst_size;
    wire read_n_write, 
         begin_transaction, end_transaction, data_valid, busy, error;

    // define regs as a workaround of the inout pin
    reg[31:0] address_data_reg;
    reg data_valid_reg;
    reg end_transaction_reg;

    // assign values of the driver regs to the wires that will then be mapped to the inout ports
    assign address_data = address_data_reg;
    assign data_valid = data_valid_reg;
    assign end_transaction = end_transaction_reg;
 
    // define out signals as wires
    output wire done;
    output wire[31:0] result;
    
    // instantiate component
    ramDmaCi #(.customId(8'd27)) dut
        (
            .reset(reset),
            .clock(clock),
            .start(start),
            .valueA(valueA),
            .valueB(valueB),
            .ciN(CiN),
            .address_data(address_data),
            .byte_enables(byte_enables),
            .burst_size(burst_size),
            .read_n_write(read_n_write),
            .begin_transaction(begin_transaction),
            .end_transaction(end_transaction),
            .data_valid(data_valid),
            .busy(busy),
            .error(error),
            .done(done),
            .result(result)
        );

    // Set the rst to 1. keep the rst to 1 for 4 cycles. Set the reset to 0. Start "forever" with the clock
    initial
    begin
        reset = 1'b1;
        clock = 1'b0;
        repeat (4) #5 clock = ~clock;
        reset = 1'b0;
        forever #5 clock = ~clock;
    end

    initial
    begin

        // set CiN to the custom instruction and start to 1
        start = 1;
        CiN = 8'd27;

        // Configurations:
        // set the Block size
        valueA[9] = 1;
        valueA[12:10] = 3'd3;
        valueB[9:0] = 10'd5;
        data_valid_reg = 1'b0;
        address_data_reg = 32'b0;
        end_transaction_reg = 1'b0; 
        repeat(3) @(negedge clock);

        // set the burst size
        valueA[12:10] = 3'd4;
        valueB[7:0] = 3'd1; // busrtSize = 2;
        repeat(3) @(negedge clock);

        // set the memory base address
        valueA[12:10] = 3'd2;
        valueB[8:0] = 9'b0;
        repeat(3) @(negedge clock);

        // set the bus base address
        valueA[12:10] = 3'd1;
        valueB[31:0] = 32'd0;
        repeat(3) @(negedge clock);

        // set the control reg to initialize a writing into the CiMem
        valueA[12:10] = 3'd5;
        valueB[1:0] = 1'd1;
        repeat(3) @(negedge clock);
        valueA[31:0] = 32'b0;
        valueB[31:0] = 32'b0;

        // start sending data to the dma
        data_valid_reg = 1'b1; // driven by two drives. In DMAController is set to zero.
        address_data_reg = 32'd1;
        repeat(1) @(negedge clock);
        address_data_reg = 32'd2;
        repeat(1) @(negedge clock);
        address_data_reg = 32'd3;
        repeat(1) @(negedge clock);
        address_data_reg = 32'd4;
        repeat(1) @(negedge clock);
        address_data_reg = 32'd5;
        repeat(1) @(posedge clock);
        data_valid_reg = 1'b0;
        end_transaction_reg = 1'b1;
        repeat(1) @(posedge clock);
        end_transaction_reg = 1'b0;
        repeat(3) @(negedge clock);
        
        // set start to zero
        start = 1'b0;
        repeat(3) @(negedge clock);
        $finish;

    end

initial 
begin
    $dumpfile("ramDmaCi.vcd");
    $dumpvars(0, dut);
end
endmodule

lab-5/virtual_prototype/modules/DMA/ramDmaCi.vcd
$date
	Mon Apr 15 13:01:33 2024
$end
$version
	Icarus Verilog
$end
$timescale
	1s
$end
$scope module ramDmaCi_tb $end
$scope module dut $end
$var wire 32 ! address_data [31:0] $end
$var wire 1 " busy $end
$var wire 4 # byte_enables [3:0] $end
$var wire 8 $ ciN [7:0] $end
$var wire 1 % clock $end
$var wire 1 & data_valid $end
$var wire 1 ' done $end
$var wire 1 ( end_transaction $end
$var wire 1 ) error $end
$var wire 1 * is_valid $end
$var wire 1 + reset $end
$var wire 32 , result [31:0] $end
$var wire 1 - start $end
$var wire 32 . valueA [31:0] $end
$var wire 32 / valueB [31:0] $end
$var wire 2 0 status [1:0] $end
$var wire 32 1 resultMem [31:0] $end
$var wire 32 2 resultDMA [31:0] $end
$var wire 1 3 read_n_write $end
$var wire 1 4 memWriteEnable $end
$var wire 32 5 memDataOut [31:0] $end
$var wire 32 6 memDataIn [31:0] $end
$var wire 9 7 memAddress [8:0] $end
$var wire 1 8 is_memory $end
$var wire 1 9 doneMem $end
$var wire 1 : doneDMA $end
$var wire 32 ; dataOutA [31:0] $end
$var wire 8 < burst_size [7:0] $end
$var wire 1 = begin_transaction $end
$var parameter 8 > customId $end
$var reg 2 ? counter [1:0] $end
$scope module dmaController $end
$var wire 32 @ address_data [31:0] $end
$var wire 1 " busy $end
$var wire 4 A byte_enables [3:0] $end
$var wire 1 % clock $end
$var wire 3 B configurationBits [2:0] $end
$var wire 1 & data_valid $end
$var wire 1 ( end_transaction $end
$var wire 1 ) error $end
$var wire 1 C grantRequest $end
$var wire 9 D memAddress [8:0] $end
$var wire 32 E memDataOut [31:0] $end
$var wire 1 + reset $end
$var wire 2 F status [1:0] $end
$var wire 1 * validInstruction $end
$var wire 1 G writeEnable $end
$var wire 32 H writeSettings [31:0] $end
$var wire 1 3 read_n_write $end
$var wire 32 I readSettings [31:0] $end
$var wire 1 4 memWriteEnable $end
$var wire 32 J memDataIn [31:0] $end
$var wire 1 K busRequest $end
$var wire 8 L burst_size [7:0] $end
$var wire 1 = begin_transaction $end
$var parameter 3 M C2R $end
$var parameter 3 N CLOSE $end
$var parameter 3 O IDLE $end
$var parameter 3 P INIT $end
$var parameter 3 Q READ $end
$var parameter 3 R REQUEST $end
$var parameter 3 S WRITE $end
$var reg 10 T blockCounter [9:0] $end
$var reg 10 U blockCounterCurr [9:0] $end
$var reg 10 V blockSize [9:0] $end
$var reg 9 W burstCounter [8:0] $end
$var reg 9 X burstSize [8:0] $end
$var reg 32 Y busAddress [31:0] $end
$var reg 32 Z busStart [31:0] $end
$var reg 2 [ controlRegister [1:0] $end
$var reg 9 \ memAddress_r [8:0] $end
$var reg 3 ] memCounter [0:2] $end
$var reg 9 ^ memoryStart [8:0] $end
$var reg 3 _ state [2:0] $end
$var reg 2 ` statusRegister [1:0] $end
$upscope $end
$scope module memory $end
$var wire 9 a addressA [8:0] $end
$var wire 9 b addressB [8:0] $end
$var wire 1 % clockA $end
$var wire 1 c clockB $end
$var wire 32 d dataInA [31:0] $end
$var wire 32 e dataInB [31:0] $end
$var wire 1 f writeEnableA $end
$var wire 1 4 writeEnableB $end
$var parameter 32 g bitwidth $end
$var parameter 32 h nrOfEntries $end
$var parameter 32 i readAfterWrite $end
$var reg 32 j dataOutA [31:0] $end
$var reg 32 k dataOutB [31:0] $end
$upscope $end
$upscope $end
$upscope $end
$enddefinitions $end
$comment Show the parameter values. $end
$dumpall
b0 i
b1000000000 h
b100000 g
b101 S
b1 R
b11 Q
b10 P
b0 O
b100 N
b110 M
b11011 >
$end
#0
$dumpvars
bx k
bx j
0f
bx e
bx0000000101 d
1c
bx b
bx a
bx `
bx _
bx ^
b0 ]
bx \
bx [
bx Z
bx Y
bx X
bx W
bx V
bx U
bx T
bx L
xK
bx J
b0xxxxxxxxxx I
bx0000000101 H
1G
bx F
bx E
bx D
zC
b11 B
bz A
bx @
bx ?
x=
bx <
bx ;
1:
09
08
bx 7
bx 6
bx 5
04
x3
b0xxxxxxxxxx 2
b0 1
bx 0
bx0000000101 /
bx0111xxxxxxxxx .
1-
b0xxxxxxxxxx ,
1+
1*
z)
x(
1'
0&
0%
b11011 $
bz #
z"
bx !
$end
#5
b0 ,
b0 2
b0 I
b0 <
b0 L
0(
0K
0=
03
b0 5
b0 E
b0 e
b0 !
b0 @
b0 [
b0 0
b0 F
b0 `
b0 X
b0 V
b0 ^
b0 Z
b0 7
b0 D
b0 b
b0 \
b0 Y
b0 T
b0 W
b0 _
0c
b0 ?
1%
#10
1c
0%
#15
0c
1%
#20
1c
0+
0%
#25
b101 ,
b101 2
b101 I
b101 V
b1 ?
0c
1%
#30
b0 ,
b0 2
b0 I
b100 B
1c
bx0000000001 /
bx0000000001 H
bx0000000001 d
bx1001xxxxxxxxx .
0%
#35
b10 ,
b10 2
b10 I
b10 ?
b10 X
0c
1%
#40
1c
0%
#45
b0 ?
0c
1%
#50
1c
0%
#55
b1 ?
0c
1%
#60
b0 ,
b0 2
b0 I
b10 B
1c
bx0000000000 /
bx0000000000 H
bx0000000000 d
bx0101xxxxxxxxx .
0%
#65
b10 ?
0c
1%
#70
1c
0%
#75
b0 ?
0c
1%
#80
1c
0%
#85
b1 ?
0c
1%
#90
b1 B
1c
b0 /
b0 H
b0 d
bx0011xxxxxxxxx .
0%
#95
b10 ?
0c
1%
#100
1c
0%
#105
b0 ?
0c
1%
#110
1c
0%
#115
b1 ?
0c
1%
#120
b101 B
1c
b1 /
b1 H
b1 d
bx1011xxxxxxxxx .
0%
#125
b1 [
b10 ?
0c
1%
#130
1c
0%
#135
b1 ,
b1 2
b1 I
1K
b0 ?
b1 _
b1 0
b1 F
b1 `
0c
1%
#140
1c
0%
#145
b1 ?
0c
1%
#150
b0 2
b0 I
0'
bx ,
09
0:
bx 1
18
b0 a
0G
b0 B
1c
b0x 5
b0x E
b0x e
b0x !
b0x @
x&
b0 /
b0 H
b0 d
b0 .
0%
#155
1'
19
b10 ?
0c
1%
#160
1c
b0x0 5
b0x0 E
b0x0 e
b0x0 !
b0x0 @
0%
#165
0'
09
b0 ?
0c
1%
#170
1c
b0xx 5
b0xx E
b0xx e
b0xx !
b0xx @
0%
#175
b1 ?
0c
1%
#180
1c
b0x00 5
b0x00 E
b0x00 e
b0x00 !
b0x00 @
0%
#185
1'
19
b10 ?
0c
1%
#190
1c
b0x0x 5
b0x0x E
b0x0x e
b0x0x !
b0x0x @
0%
#195
0'
09
b0 ?
0c
x(
0&
1%
#200
1c
0%
#205
b1 ?
0c
0(
1%
#210
1c
0%
#215
1'
19
b10 ?
0c
1%
#220
1c
0%
#225
0'
09
b0 ?
0c
1%
#230
b0 ,
b0 1
0*
1c
0-
0%
#235
b1 ?
0c
1%
#240
1c
0%
#245
b10 ?
0c
1%
#250
1c
0%
#255
b0 ?
0c
1%
